pdfreadermcp/__init__.py
pdfreadermcp/__main__.py
pdfreadermcp/server.py
pdfreadermcp/tools/__init__.py
pdfreadermcp/tools/pdf_image_converter.py
pdfreadermcp/tools/pdf_metadata.py
pdfreadermcp/tools/pdf_ocr.py
pdfreadermcp/tools/pdf_operations.py
pdfreadermcp/tools/pdf_optimizer.py
pdfreadermcp/tools/pdf_reader.py
pdfreadermcp/tools/pdf_text_search.py
pdfreadermcp/utils/__init__.py
pdfreadermcp/utils/cache.py
pdfreadermcp/utils/chunker.py
pdfreadermcp/utils/file_handler.py
pdfmcp_tools-0.1.1.dist-info/METADATA
pdfmcp_tools-0.1.1.dist-info/WHEEL
pdfmcp_tools-0.1.1.dist-info/entry_points.txt
pdfmcp_tools-0.1.1.dist-info/RECORD
