Metadata-Version: 2.4
Name: pdfmcp-tools
Version: 0.1.1
Summary: MCP server for comprehensive PDF processing with 18 specialized tools
Project-URL: Homepage, https://github.com/lihongwen/pdfreadermcp
Project-URL: Repository, https://github.com/lihongwen/pdfreadermcp.git
Project-URL: Issues, https://github.com/lihongwen/pdfreadermcp/issues
Project-URL: Documentation, https://github.com/lihongwen/pdfreadermcp#readme
Project-URL: Changelog, https://github.com/lihongwen/pdfreadermcp/releases
Author-email: lihongwen <1062316792@qq.com>
Maintainer-email: lihongwen <1062316792@qq.com>
License: MIT
Keywords: document-processing,fastmcp,image-conversion,mcp,ocr,pdf,pdf-optimization,pdf-processing,pdf-tools,tesseract,text-extraction
Classifier: Development Status :: 4 - Beta
Classifier: Environment :: Console
Classifier: Framework :: AsyncIO
Classifier: Intended Audience :: Developers
Classifier: License :: OSI Approved :: MIT License
Classifier: Natural Language :: Chinese (Simplified)
Classifier: Natural Language :: English
Classifier: Operating System :: OS Independent
Classifier: Programming Language :: Python :: 3
Classifier: Programming Language :: Python :: 3 :: Only
Classifier: Programming Language :: Python :: 3.11
Classifier: Programming Language :: Python :: 3.12
Classifier: Programming Language :: Python :: 3.13
Classifier: Topic :: Multimedia :: Graphics :: Graphics Conversion
Classifier: Topic :: Office/Business :: Office Suites
Classifier: Topic :: Software Development :: Libraries :: Python Modules
Classifier: Topic :: Text Processing :: General
Requires-Python: >=3.11
Requires-Dist: mcp[cli]>=1.2.0
Requires-Dist: pdf2image>=1.16.0
Requires-Dist: pdfplumber>=0.11.0
Requires-Dist: pillow>=10.0.0
Requires-Dist: pypdf>=4.0.0
Requires-Dist: pytesseract>=0.3.10
Provides-Extra: dev
Requires-Dist: black>=25.0.0; extra == 'dev'
Requires-Dist: isort>=6.0.0; extra == 'dev'
Requires-Dist: mypy>=1.18.0; extra == 'dev'
Requires-Dist: pytest-asyncio>=1.2.0; extra == 'dev'
Requires-Dist: pytest-cov>=7.0.0; extra == 'dev'
Requires-Dist: pytest-mock>=3.15.0; extra == 'dev'
Requires-Dist: pytest>=8.4.0; extra == 'dev'
Requires-Dist: ruff>=0.13.0; extra == 'dev'
